<annotation>
	<folder></folder>
	<filename>FishDataset286_png.rf.eb5bfd3cbaa614014f820387af2a7a7e.jpg</filename>
	<path>FishDataset286_png.rf.eb5bfd3cbaa614014f820387af2a7a7e.jpg</path>
	<source>
		<database>roboflow.ai</database>
	</source>
	<size>
		<width>416</width>
		<height>416</height>
		<depth>3</depth>
	</size>
	<segmented>0</segmented>
	<object>
		<name>Serranidae -Groupers-</name>
		<pose>Unspecified</pose>
		<truncated>0</truncated>
		<difficult>0</difficult>
		<occluded>0</occluded>
		<bndbox>
			<xmin>13</xmin>
			<xmax>404</xmax>
			<ymin>103</ymin>
			<ymax>333</ymax>
		</bndbox>
	</object>
</annotation>
