<annotation>
	<folder></folder>
	<filename>FishDataset692_png.rf.ea12b0fcb94caae6332264728ac8a883.jpg</filename>
	<path>FishDataset692_png.rf.ea12b0fcb94caae6332264728ac8a883.jpg</path>
	<source>
		<database>roboflow.ai</database>
	</source>
	<size>
		<width>416</width>
		<height>416</height>
		<depth>3</depth>
	</size>
	<segmented>0</segmented>
	<object>
		<name>Serranidae -Groupers-</name>
		<pose>Unspecified</pose>
		<truncated>0</truncated>
		<difficult>0</difficult>
		<occluded>0</occluded>
		<bndbox>
			<xmin>12</xmin>
			<xmax>408</xmax>
			<ymin>98</ymin>
			<ymax>308</ymax>
		</bndbox>
	</object>
</annotation>
